{
  "Disabled": false,
  "Testing": false,
  "ScheduledForDeletion": false,
  "InstalledFromUrl": "OFFICIAL",
  "IsThirdParty": false,
  "EffectiveVersion": "1.2.1.0",
  "IsAvailableForTesting": false,
  "Author": "NightmareXIV",
  "Name": "XIV Instant Messenger",
  "Punchline": "A direct message manager made in fashion of WoW Instant Messenger.",
  "Description": "Features:\n- Opes a direct message window when you message someone or they message you\n- Each window contains your DM chat with certain person\n- Open and cycle through recent chats with a hotkey\n- Execute emote commands on a player from their DM window without needing to manually target them\n- Automatically record your chat log in an easy to read text file\n- Fully customizable styles",
  "Changelog": null,
  "Tags": null,
  "CategoryTags": null,
  "IsHide": false,
  "InternalName": "Messenger",
  "AssemblyVersion": "1.2.1.0",
  "TestingAssemblyVersion": null,
  "IsTestingExclusive": false,
  "RepoUrl": "https://github.com/NightmareXIV/XIVInstantMessenger",
  "ApplicableVersion": "any",
  "DalamudApiLevel": 8,
  "DownloadCount": 12995,
  "LastUpdate": 1673464901,
  "DownloadLinkInstall": "https://kamori.goats.dev/Plugin/Download/Messenger?isUpdate=False&isTesting=False&branch=api8&isDip17=True",
  "DownloadLinkUpdate": "https://raw.githubusercontent.com/goatcorp/DalamudPlugins/api8/plugins/Messenger/latest.zip",
  "DownloadLinkTesting": "https://kamori.goats.dev/Plugin/Download/Messenger?isUpdate=False&isTesting=True&branch=api8&isDip17=True",
  "LoadRequiredState": 0,
  "LoadSync": false,
  "LoadPriority": 0,
  "CanUnloadAsync": false,
  "ImageUrls": null,
  "IconUrl": null,
  "AcceptsFeedback": false,
  "FeedbackMessage": null,
  "_isDip17Plugin": true,
  "_Dip17Channel": "stable"
}